Metadata-Version: 2.1
Name: django-permafrost
Version: 0.2.23
Summary: Adds Client Definable Permissions to Django
Home-page: https://github.com/renderbox/django-permafrost/
Author: Grant Viklund
Author-email: renderbox@gmail.com
License: MIT license
Keywords: django,app
Platform: UNKNOWN
Classifier: Development Status :: 3 - Alpha
Classifier: Intended Audience :: Developers
Classifier: Programming Language :: Python :: 3 :: Only
Classifier: Programming Language :: Python :: 3.6
Classifier: Programming Language :: Python :: 3.7
Requires-Python: >=3.7
Requires-Dist: Django (<4.1,>=3.0)
Requires-Dist: jsonfield
Provides-Extra: build
Requires-Dist: setuptools ; extra == 'build'
Requires-Dist: wheel ; extra == 'build'
Requires-Dist: twine ; extra == 'build'
Requires-Dist: mistune (<2.0.0) ; extra == 'build'
Requires-Dist: m2r ; extra == 'build'
Provides-Extra: dev
Requires-Dist: django-crispy-forms ; extra == 'dev'
Requires-Dist: django-allauth ; extra == 'dev'
Requires-Dist: django-extensions ; extra == 'dev'
Requires-Dist: django-rest-framework ; extra == 'dev'
Provides-Extra: docs
Requires-Dist: recommonmark ; extra == 'docs'
Requires-Dist: m2r ; extra == 'docs'
Requires-Dist: django-extensions ; extra == 'docs'
Requires-Dist: coverage ; extra == 'docs'
Requires-Dist: Sphinx ; extra == 'docs'
Requires-Dist: rstcheck ; extra == 'docs'
Requires-Dist: sphinx-rtd-theme ; extra == 'docs'
Provides-Extra: prod
Provides-Extra: test
